transformer_directed_evolution/__init__.py
transformer_directed_evolution/evolution_director.py
transformer_directed_evolution-0.0.3.dist-info/METADATA
transformer_directed_evolution-0.0.3.dist-info/WHEEL
transformer_directed_evolution-0.0.3.dist-info/licenses/LICENSE
transformer_directed_evolution-0.0.3.dist-info/RECORD
