Metadata-Version: 2.4
Name: transformer-directed-evolution
Version: 0.0.3
Summary: Directed Evolution with Transformer
Project-URL: Homepage, https://pypi.org/project/transformer-directed-evolution/
Project-URL: Repository, https://github.com/lucidrains/transformer-directed-evolution
Author-email: Phil Wang <lucidrains@gmail.com>
License: MIT License
License-File: LICENSE
Keywords: artificial intelligence,attention mechanisms,deep learning,evolution
Classifier: Development Status :: 4 - Beta
Classifier: Intended Audience :: Developers
Classifier: License :: OSI Approved :: MIT License
Classifier: Programming Language :: Python :: 3.9
Classifier: Topic :: Scientific/Engineering :: Artificial Intelligence
Requires-Python: >=3.9
Requires-Dist: assoc-scan>=0.0.2
Requires-Dist: einops>=0.8.0
Requires-Dist: evolutionary-policy-optimization>=0.0.29
Requires-Dist: torch>=2.0
Requires-Dist: wandb
Requires-Dist: x-transformers>=2.0.0
Provides-Extra: examples
Requires-Dist: tqdm; extra == 'examples'
Requires-Dist: wandb; extra == 'examples'
Provides-Extra: test
Requires-Dist: pytest; extra == 'test'
